tabplot/__init__.py
tabplot/barplot.py
tabplot/histogram.py
tabplot/plot.py
tabplot/postprocessing.py
tabplot/utils.py
tabplot-0.2.data/scripts/tabplot
tabplot-0.2.dist-info/LICENSE.md
tabplot-0.2.dist-info/METADATA
tabplot-0.2.dist-info/WHEEL
tabplot-0.2.dist-info/top_level.txt
tabplot-0.2.dist-info/RECORD
