Metadata-Version: 2.1
Name: tabplot
Version: 0.2
Summary: Tabplot: A wrapper over matplotlib for reading tabular (csv) text files.
Author: Jayghosh Rao
Author-email: jayghoshter@gmail.com
License: MIT
Classifier: Programming Language :: Python :: 3
Classifier: License :: OSI Approved :: MIT License
Classifier: Operating System :: OS Independent
Requires-Python: >=3.9
License-File: LICENSE.md
Requires-Dist: matplotlib (==3.6.2)
Requires-Dist: numexpr (==2.8.4)
Requires-Dist: numpy (==1.24.1)
Requires-Dist: rich (==13.0.0)
Requires-Dist: scikit-learn (==1.2.0)
Requires-Dist: scipy (==1.9.3)
